gcp_accessor/__init__.py
gcp_accessor/bq_accessor.py
gcp_accessor/gcs_accessor.py
gcp_accessor-0.0.6.dist-info/LICENSE.txt
gcp_accessor-0.0.6.dist-info/METADATA
gcp_accessor-0.0.6.dist-info/WHEEL
gcp_accessor-0.0.6.dist-info/top_level.txt
gcp_accessor-0.0.6.dist-info/RECORD
