Metadata-Version: 2.1
Name: gcp-accessor
Version: 0.0.6
Summary: Accessor to Google Cloud Storage and Big Query
Home-page: https://github.com/tetsuya0617/gcputils
Author: Tetsuya Hirata
Author-email: tetsuya.hirata@classi.jp
Maintainer: Tetsuya Hirata
Maintainer-email: tetsuya.hirata@classi.jp
License: MIT
Platform: UNKNOWN
Classifier: Development Status :: 3 - Alpha
Classifier: License :: OSI Approved :: MIT License
Classifier: Programming Language :: Python :: 3.5
Classifier: Programming Language :: Python :: 3.6
Classifier: Programming Language :: Python :: 3.7
Classifier: Operating System :: OS Independent
Classifier: Topic :: Utilities
Requires-Dist: google-cloud-storage
Requires-Dist: google-cloud-bigquery
